
[
    {
        "code": "MTH 1554",
        "name": "Calculus I",
        "description": "A detailed study of limits, continuity, derivatives of algebraic and transcendental functions, applications of derivatives, numerical techniques, integrals and the Fundamental Theorem of Calculus.",
        "prerequisites": ["MTH 1441 with a grade of (C) or higher, or MTH 1331 and MTH 1332, each with a grade of (C) or higher or placement &&& Satisfies the university general education requirement in the formal reasoning knowledge foundation area."],
        "difficulty": 2,
        "review": "Calc 1 review WIP.",
        "hours": 4
    },
    {
        "code": "MTH 1555",
        "name": "Calculus II",
        "description": "A detailed study of methods of integration, applications of the integrals, improper integrals, sequences, series and power series, polar coordinates and parametric curves.",
        "prerequisites": ["MTH 1554 with a grade of (C) or higher &&& Satisfies the university general education requirement for the knowledge applications integration area. Prerequisites for knowledge applications: completion of the university general education requirement in the formal reasoning knowledge foundation area."],
        "difficulty": 3,
        "review": "I struggled with memorizing all the Integration techniques, there were a lot of them. This class focuses heavily on this. I recommend getting ahead of this class, Memorizing everything helps when you practice problems. Practice problems outside of HW and lecture and practice every technique, you are looking for certain identifiers in the question that will help you pick which technique to use and practicing helps reinforce that memory of which is which - Austin W",
        "hours": 4
    },
    {
        "code": "MTH 2775",
        "name": "Linear Algebra",
        "description": "Formal models of computation, ranging from finite state automata to Turing machines. Computational models are used to discuss the languages recognized by these machines and address issues of computability.",
        "prerequisites": ["MTH 1555 with a grade of (C) or higher"],
        "difficulty": 3,
        "review": "Following Discrete mathematics with this class is recommended.",
        "hours": 4
    },
    {
        "code": "APM 2663",
        "name": "Discrete Mathematics",
        "description": "Concepts and methods of discrete mathematics with an emphasis on their application to computer science. Logic and proofs, sets and relations, algorithms, induction and recursion, combinatorics, graphs and trees.",
        "prerequisites": ["MTH 1555 with a grade of (C) or higher"],
        "difficulty": 1,
        "review": " ",
        "hours": 4
    },
    {
        "code": "STA 2226",
        "name": "Applied Probability and Statistics",
        "description": " ",
        "prerequisites": ["MTH 1222 with a grade of (C) or higher or MTH 1554 with a grade of (C) or higher"],
        "difficulty": 1,
        "review": " ",
        "hours": 4
    },
    {
        "code": "CSI 1420",
        "name": "Introduction to C Programming and Unix",
        "description": " ",
        "prerequisites": ["MTH 1554"],
        "difficulty": 1,
        "review": "Not too difficult of a class, with simple assignments to learn coding in not just the language, but also fundamental concepts for all coding languages, as well as a group course project. This project will require solid knowledge on all topics, just make sure to not procrastinate on this or any other assignments. - Nicholas Sakowski",
        "hours": 4
    },
    {
        "code": "CSI 2300",
        "name": "Object-Oriented Computing",
        "description": " ",
        "prerequisites": ["EGR 1400 or CSI 1300 or CSI 1320 or CSI 1420 with a grade of C or higher"],
        "difficulty": 1,
        "review": " ",
        "hours": 4
    },
    {
        "code": "CSI 2310",
        "name": "Data Structures",
        "description": " ",
        "prerequisites": ["CSI 2300"],
        "difficulty": 1,
        "review": " ",
        "hours": 4
    },
    {
        "code": "CSI 2470",
        "name": "Introduction to Computer Networks",
        "description": " ",
        "prerequisites": ["CSI 1320 or CSI 1420"],
        "difficulty": 1,
        "review": " ",
        "hours": 4
    },
    {
        "code": "CSI 2999",
        "name": "Sophomore Project",
        "description": " ",
        "prerequisites": ["CSI 2300 with a grade of C or higher"],
        "difficulty": 1,
        "review": " ",
        "hours": 2
    },
    {
        "code": "CSI 3370",
        "name": "Software Engineering and Practice",
        "description": " ",
        "prerequisites": ["CSI 2300"],
        "difficulty": 1,
        "review": " ",
        "hours": 4
    },
    {
        "code": "CSI 3430",
        "name": "Theory of Computation",
        "description": " ",
        "prerequisites": ["APM 2663"],
        "difficulty": 1,
        "review": " ",
        "hours": 4
    },
    {
        "code": "CSI 3450",
        "name": "Database Design and Implementation",
        "description": " ",
        "prerequisites": ["CSI 2290 or CSI 2300"],
        "difficulty": 1,
        "review": " ",
        "hours": 4
    },
    {
        "code": "CSI 3610",
        "name": "Design and Analysis of Algorithms",
        "description": " ",
        "prerequisites": ["(CSI 2310 or CSI 2290), APM 2663, & Major standing"],
        "difficulty": 1,
        "review": " ",
        "hours": 4
    },
    {
        "code": "CSI 3640",
        "name": "Computer Organization",
        "description": "",
        "prerequisites": ["(CSI 2290 or CSI 2310 or EGR 2400) & Major Standing"],
        "difficulty": 1,
        "review": "",
        "hours": 4
    },
    {
        "code": "CSI 4350",
        "name": "Programming Languages",
        "description": "",
        "prerequisites": ["CSI 2310 and CSI 3430 & Major Standing"],
        "difficulty": 1,
        "review": "",
        "hours": 4
    },
    {
        "code": "CSI 4480",
        "name": "Information Security Practice",
        "description": "",
        "prerequisites": ["CSI 2470 & Major Standing"],
        "difficulty": 1,
        "review": "",
        "hours": 4
    },
    {
        "code": "CSI 4500",
        "name": "Fundamentals of Operating Systems",
        "description": "",
        "prerequisites": ["CSI 2310, CSI 3640 & Major Standing"],
        "difficulty": 1,
        "review": "",
        "hours": 4
    },
    {
        "code": "CSI 4650",
        "name": "Parallel and Distributed Computing",
        "description": "",
        "prerequisites": ["CSI 3640 & Majore Standing"],
        "difficulty": 1,
        "review": "",
        "hours": 4
    },
    {
        "code": "CSI 4999",
        "name": "Senior Capstone Project",
        "description": "",
        "prerequisites": ["CSI 3370, CSI 3450, (CSI 3150 or CSI 3500 or CSI 3520 or CSI 3610 or CSI 3620 or CSI 3640) & Major Standing"],
        "difficulty": 1,
        "review": "",
        "hours": 4
    },
    {
        "code": "BIO 3400",
        "name": "Genetics",
        "description": "",
        "prerequisites": ["BIO 1200 with a grade of (C) or higher"],
        "difficulty": 1,
        "review": "",
        "hours": 4
    },
    {
        "code": "CSI 4780",
        "name": "Bioinformatics",
        "description": "",
        "prerequisites": ["Major standing"],
        "difficulty": 1,
        "review": "",
        "hours": 4
    },
    {
        "code": "CSI 4460",
        "name": "Information Security",
        "description": "",
        "prerequisites": ["CSI 2470 & Major Standing"],
        "difficulty": 1,
        "review": "",
        "hours": 4
    },
    {
        "code": "CSI 4700",
        "name": "Software Security",
        "description": "",
        "prerequisites": ["Major standing"],
        "difficulty": 1,
        "review": "",
        "hours": 4
    },
    {
        "code": "APM 4347",
        "name": "Mathematics of Cryptology",
        "description": "",
        "prerequisites": ["MTH 3002 or  APM 3610 or CSI 3610 with grade of (C) or higher, or permission of department."],
        "difficulty": 1,
        "review": "",
        "hours": 4

    },
    {
        "code": "CSI 4130",
        "name": "Computational Intelligence",
        "description": "",
        "prerequisites": ["(EGR 2600 or STA 2221 or STA 2226) and (CSI 3610 or CSI 3620) & Major Standing"],
        "difficulty": 1,
        "review": ""

    },
    {
        "code": "CSI 4810",
        "name": "Information Retrieval and Knowledge Discovery",
        "description": "",
        "prerequisites": ["(APM 2555 or MTH 2775) and (EGR 2600 or STA 2221 or STA 2226) & Major Standing"],
        "difficulty": 1,
        "review": ""

    },
    {
        "code": "CSI 3660",
        "name": "Systems Administration",
        "description": "",
        "prerequisites": ["CSI 1320 or CSI 1420 & Major Standing"],
        "difficulty": 1,
        "review": ""

    },
    {
        "code": "CSI 4660",
        "name": "Advanced Systems Administration",
        "description": "",
        "prerequisites": ["CSI 3660 & Major Standing"],
        "difficulty": 1,
        "review": ""
        
    },
    {
        "code": "CSI 3380",
        "name": "Game Design",
        "description": "",
        "prerequisites": [],
        "difficulty": 1,
        "review": "",
        "hours": 4
    },
    {
        "code": "CSI 4380",
        "name": "Game Programming",
        "description": "",
        "prerequisites": ["CSI 1300, CSI 1320, CSI 1420 or EGR 1400 & Major Standing"],
        "difficulty": 1,
        "review": "",
        "hours": 4
    },
    {
        "code": "CSI 4230",
        "name": "Mobile Application Development",
        "description": "",
        "prerequisites": ["CSI 2300 & Major Standing"],
        "difficulty": 1,
        "review": "",
        "hours": 4
    },
    {
        "code": "CSI 3150",
        "name": "Web and Mobile Systems",
        "description": "",
        "prerequisites": ["CSI 2300 & Major Standing"],
        "difficulty": 1,
        "review": "",
        "hours": 4
    },
    {
        "code": "CSI 4160",
        "name": "Integreated Computing Systems",
        "description": "",
        "prerequisites": ["CSI 2470, CSI 3150, CSI 3450 & Major Standing"],
        "difficulty": 1,
        "review": "",
        "hours": 4
    },
    {
        "code": "CSI 1320",
        "name": "Intro to Python and Unix",
        "description": "",
        "prerequisites": ["MTH 0662"],
        "difficulty": 1,
        "review": "",
        "hours": 4
    },
    {
        "code": "WRT 1060",
        "name": "Writing Foundations",
        "description": "",
        "prerequisites": ["WRT 1050 with a grade of (C) or higher or placement"],
        "difficulty": 1,
        "review": "",
        "hours": 4
    },
    {
        "code": "BIO 1200",
        "name": "Biology I",
        "description": "",
        "prerequisites": ["Satisfies the university general education requirement in the natural science and technology knowledge exploration area."],
        "difficulty": 1,
        "review": "",
        "hours": 4
    },
    {
        "code": "BIO 1300",
        "name": "Biology II",
        "description": "",
        "prerequisites": ["BIO 1200 recommended & Satisfies the university general education requirement in the natural science and technology knowledge exploration area."],
        "difficulty": 1,
        "review": "",
        "hours": 4
    },
    {
        "code": "CHM 1440",
        "name": "General Chemistry I",
        "description": "",
        "prerequisites": ["Score of 22 or higher on ACT mathematics exam or score of 550 or higher on SAT mathematics exam or MTH 0662 with a grade of C or better or equivalent or placement above MTH 0662 &&& CHM 1440 and CHM 1470 together satisfy the university general education requirement in the natural science and technology knowledge exploration area."],
        "difficulty": 1,
        "review": "",
        "hours": 4
    },
    {
        "code": "PHY 1510",
        "name": "Introductory Physics I",
        "description": "",
        "prerequisites": ["MTH 1554 & PHY 1510 and PHY 1100 together satisfy the university general education requirement in the natural science and technology knowledge exploration area."],
        "difficulty": 1,
        "review": "",
        "hours": 4
    },
    {
        "code": "CSI 4140",
        "name": "Deep Learning and Applications",
        "description": "",
        "prerequisites": ["(APM 2555 or MTH 2775) and ( EGR 2600 or STA 2221 or STA 2226) & Major Standing"],
        "difficulty": 1,
        "review": "",
        "hours": 4

    },
    {
        "code": "CSI 4170",
        "name": "Machine Learning",
        "description": "",
        "prerequisites": ["(APM 2555 or MTH 2775) and (EGR 2600 or STA 2221 or STA 2226) & Major Standing"],
        "difficulty": 1,
        "review": "",
        "hours": 4
    },
    {
        "code": "CSI 4180",
        "name": "Natural Language Processing",
        "description": "",
        "prerequisites": ["(APM 2555 or MTH 2775) and (EGR 2600 or STA 2221 or STA 2226) & Major Standing"],
        "difficulty": 1,
        "review": "",
        "hours": 4

    },
    {
        "code": "CSI 4550",
        "name": "Visual Computing",
        "description": "",
        "prerequisites": ["(APM 2555 or MTH 2775) and (EGR 2600 or STA 2221 or STA 2226) & Major Standing"],
        "difficulty": 1,
        "review": "",
        "hours": 4

    },
    {
        "code": "MTH 0662",
        "name": "Intermediate Algebra",
        "description": "",
        "prerequisites": ["MTH 0661 with a grade of (C) or higher or placement exam"],
        "difficulty": 1,
        "review": "",
        "hours": 4

    },
    {
        "code": "MTH 0661",
        "name": "Elementary Algebra",
        "description": "",
        "prerequisites": [],
        "difficulty": 1,
        "review": "",
        "hours": 4

    }
 
    
]
